aedev/tpl_app/__init__.py
aedev/tpl_app/templates/de_tpl_main.py
aedev/tpl_app/templates/main.kv
aedev/tpl_app/templates/requirements.txt
aedev/tpl_app/templates/de_mtp_ae_updater_moves/FStringEvalSuggestions.txt
aedev/tpl_app/templates/de_mtp_ae_updater_moves/{package_name}.ini
aedev/tpl_app/templates/de_mtp_img/app_icon.jpg
aedev/tpl_app/templates/de_mtp_loc/de/Msg.txt
aedev/tpl_app/templates/de_mtp_loc/en/Msg.txt
aedev/tpl_app/templates/de_mtp_loc/es/Msg.txt
aedev_tpl_app-0.3.13.dist-info/licenses/LICENSE.md
aedev_tpl_app-0.3.13.dist-info/METADATA
aedev_tpl_app-0.3.13.dist-info/WHEEL
aedev_tpl_app-0.3.13.dist-info/top_level.txt
aedev_tpl_app-0.3.13.dist-info/RECORD
